PythonAlloyClient/__init__.py
PythonAlloyClient/alloy_server.py
PythonAlloyClient/syntax_status.py
PythonAlloyClient/resources/org.alloytools.alloy.dist.jar
pythonalloyclient-0.1.4.dist-info/licenses/LICENSE.txt
tests/__init__.py
tests/test_syntax.py
pythonalloyclient-0.1.4.dist-info/METADATA
pythonalloyclient-0.1.4.dist-info/WHEEL
pythonalloyclient-0.1.4.dist-info/top_level.txt
pythonalloyclient-0.1.4.dist-info/RECORD
