Metadata-Version: 2.4
Name: PythonAlloyClient
Version: 0.1.4
Summary: Python Client for the Alloy Language Server
Home-page: https://github.com/mrigankpawagi/PythonAlloyClient
Author: Mrigank Pawagi
Author-email: Mrigank Pawagi <mrigankpawagi@gmail.com>
License: MIT
Project-URL: Homepage, https://github.com/mrigankpawagi/PythonAlloyClient
Classifier: Programming Language :: Python :: 3
Classifier: License :: OSI Approved :: MIT License
Classifier: Operating System :: POSIX :: Linux
Requires-Python: >=3.6
License-File: LICENSE.txt
Dynamic: author
Dynamic: home-page
Dynamic: license-file
Dynamic: requires-python
